virtual_aide/__init__.py
virtual_aide/assistreq_pws.py
virtual_aide-0.6.dist-info/METADATA
virtual_aide-0.6.dist-info/WHEEL
virtual_aide-0.6.dist-info/top_level.txt
virtual_aide-0.6.dist-info/RECORD
