Metadata-Version: 2.1
Name: virtual-aide
Version: 0.6
Summary: Required package to run assistant
Classifier: Programming Language :: Python :: 3
Classifier: License :: OSI Approved :: MIT License
Classifier: Operating System :: OS Independent
Requires-Python: >=3.6
